{"frames":{"btn_attack.png":{"frame":{"x":0,"y":0,"w":185,"h":380,"idx":0},"spriteSourceSize":{"x":0,"y":0},"sourceSize":{"w":185,"h":380}},"control_base.png":{"frame":{"x":187,"y":0,"w":200,"h":200,"idx":0},"spriteSourceSize":{"x":0,"y":0},"sourceSize":{"w":200,"h":200}},"control_knob.png":{"frame":{"x":187,"y":202,"w":95,"h":95,"idx":0},"spriteSourceSize":{"x":0,"y":0},"sourceSize":{"w":95,"h":95}}},"meta":{"app":"http:\/\/www.layabox.com","version":"1.00","format":"json","scale":1,"image":"controller.png","prefix":"controller\/"}}
